gurume/__init__.py
gurume/area_mapping.py
gurume/cache.py
gurume/cli.py
gurume/detail.py
gurume/exceptions.py
gurume/genre_mapping.py
gurume/llm.py
gurume/py.typed
gurume/restaurant.py
gurume/retry.py
gurume/search.py
gurume/server.py
gurume/suggest.py
gurume/tui.py
gurume/types.py
gurume-0.0.5.dist-info/METADATA
gurume-0.0.5.dist-info/WHEEL
gurume-0.0.5.dist-info/entry_points.txt
gurume-0.0.5.dist-info/licenses/LICENSE
gurume-0.0.5.dist-info/RECORD
