Metadata-Version: 2.4
Name: gurume
Version: 0.0.5
Author-email: narumi <toucans-cutouts0f@icloud.com>
License-File: LICENSE
Requires-Python: >=3.12
Requires-Dist: beautifulsoup4>=4.13.4
Requires-Dist: loguru>=0.7.3
Requires-Dist: lxml>=6.0.2
Requires-Dist: mcp[cli]>=1.13.0
Requires-Dist: openai>=2.14.0
Requires-Dist: tenacity>=9.1.2
Requires-Dist: textual>=6.11.0
Requires-Dist: typer>=0.16.0
